drf_user_activity_tracker/__init__.py
drf_user_activity_tracker/admin.py
drf_user_activity_tracker/apps.py
drf_user_activity_tracker/collectstatic.py
drf_user_activity_tracker/events.py
drf_user_activity_tracker/insert_log_into_database.py
drf_user_activity_tracker/models.py
drf_user_activity_tracker/serializers.py
drf_user_activity_tracker/start_logger_when_server_starts.py
drf_user_activity_tracker/tests.py
drf_user_activity_tracker/urls.py
drf_user_activity_tracker/utils.py
drf_user_activity_tracker/views.py
drf_user_activity_tracker/middleware/__init__.py
drf_user_activity_tracker/middleware/activity_tracker_middleware.py
drf_user_activity_tracker/migrations/0001_initial.py
drf_user_activity_tracker/migrations/__init__.py
drf_user_activity_tracker/templates/change_form.html
drf_user_activity_tracker/templates/charts_change_list.html
drf_user_activity_tracker-1.0.1.dist-info/LICENSE
drf_user_activity_tracker-1.0.1.dist-info/METADATA
drf_user_activity_tracker-1.0.1.dist-info/WHEEL
drf_user_activity_tracker-1.0.1.dist-info/top_level.txt
drf_user_activity_tracker-1.0.1.dist-info/RECORD
