Metadata-Version: 2.1
Name: drf-user-activity-tracker
Version: 1.0.1
Summary: A Django app to logs users activities.
Home-page: https://github.com/bigmo94
Author: Mohamad
Author-email: m.rezaie94@gmail.com
License: MIT
Platform: UNKNOWN
Classifier: Environment :: Web Environment
Classifier: Framework :: Django
Classifier: Intended Audience :: Developers
Classifier: License :: OSI Approved :: MIT License
Classifier: Operating System :: OS Independent
Classifier: Programming Language :: Python
Classifier: Programming Language :: Python :: 3
Requires-Python: >=3.8
License-File: LICENSE
